mio_lang-0.1.8.dist-info/RECORD
mio_lang-0.1.8.dist-info/WHEEL
mio_lang-0.1.8.dist-info/entry_points.txt
mio_lang-0.1.8.dist-info/top_level.txt
mio_lang-0.1.8.dist-info/DESCRIPTION.rst
mio_lang-0.1.8.dist-info/METADATA
mio_lang-0.1.8.dist-info/pydist.json
mio/utils.pyc
mio/runtime.pyc
mio/version.pyc
mio/version.py
mio/state.py
mio/main.py
mio/state.pyc
mio/runtime.py
mio/parser.pyc
mio/errors.pyc
mio/main.pyc
mio/object.pyc
mio/lexer.py
mio/trait.py
mio/lexer.pyc
mio/utils.py
mio/trait.pyc
mio/__init__.pyc
mio/parser.py
mio/errors.py
mio/__init__.py
mio/object.py
mio/termsize.pyc
mio/types/dict.pyc
mio/types/boolean.pyc
mio/types/tuple.pyc
mio/types/list.pyc
mio/types/boolean.py
mio/types/dict.py
mio/types/bytes.py
mio/types/tuple.py
mio/types/string.py
mio/types/__init__.pyc
mio/types/list.py
mio/types/string.pyc
mio/types/bytes.pyc
mio/types/number.pyc
mio/types/__init__.py
mio/types/number.py
mio/lib/iterators.mio
mio/lib/this.mio
mio/lib/functools.mio
mio/lib/antigravity.mio
mio/lib/errors.mio
mio/lib/builtins.mio
mio/lib/operators.mio
mio/lib/bootstrap/cloneable.mio
mio/lib/bootstrap/iterable.mio
mio/lib/bootstrap/object.mio
mio/lib/bootstrap/__init__.mio
mio/lib/bootstrap/comparable.mio
mio/lib/bootstrap/syntactic.mio
mio/lib/bootstrap/error.mio
mio/lib/bootstrap/range.mio
mio/lib/bootstrap/operators.mio
mio/lib/tests/test_functools.mio
mio/lib/tests/__init__.mio
mio/lib/tests/test_builtins.mio
mio/core/module.py
mio/core/continuation.py
mio/core/module.pyc
mio/core/state.py
mio/core/exception.pyc
mio/core/system.pyc
mio/core/range.py
mio/core/path.py
mio/core/state.pyc
mio/core/generator.pyc
mio/core/continuation.pyc
mio/core/parser.pyc
mio/core/file.pyc
mio/core/message.pyc
mio/core/error.py
mio/core/ffi.pyc
mio/core/file.py
mio/core/exception.py
mio/core/path.pyc
mio/core/__init__.pyc
mio/core/range.pyc
mio/core/error.pyc
mio/core/ffi.py
mio/core/parser.py
mio/core/message.py
mio/core/importer.pyc
mio/core/block.py
mio/core/__init__.py
mio/core/block.pyc
mio/core/generator.py
mio/core/importer.py
mio/core/system.py
mio/core/__pycache__/test_state.cpython-27-PYTEST.pyc
mio/traits/adaptable.py
