Metadata-Version: 2.0
Name: mio-lang
Version: 0.1.8
Summary: A Toy Programming Language written in Python
Home-page: http://bitbucket.org/prologic/mio-lang/
Author: James Mills
Author-email: James Mills, prologic at shortcircuit dot net dot au
License: MIT
Download-URL: http://bitbucket.org/prologic/mio-lang/downloads/
Keywords: toy programming language io mio message
Platform: POSIX
Classifier: Development Status :: 3 - Alpha
Classifier: Intended Audience :: Developers
Classifier: License :: OSI Approved :: MIT License
Classifier: Natural Language :: English
Classifier: Operating System :: MacOS :: MacOS X
Classifier: Operating System :: POSIX :: Linux
Classifier: Programming Language :: Python :: 2.7
Classifier: Topic :: Software Development :: Assemblers
Classifier: Topic :: Software Development :: Code Generators
Classifier: Topic :: Software Development :: Compilers
Classifier: Topic :: Software Development :: Debuggers
Classifier: Topic :: Software Development :: Interpreters
Requires-Dist: funcparserlib (==0.3.6)
